karton/memory_watcher/__init__.py
karton/memory_watcher/watcher.py
karton_memory_watcher-1.0.2.dist-info/METADATA
karton_memory_watcher-1.0.2.dist-info/WHEEL
karton_memory_watcher-1.0.2.dist-info/top_level.txt
karton_memory_watcher-1.0.2.dist-info/RECORD
