Metadata-Version: 2.2
Name: karton_memory_watcher
Version: 1.0.2
Summary: Memory watcher for karton consumers
Author-email: Rakovsky Stanislav <iam@disasm.me>
Project-URL: Homepage, https://github.com/rakovskij-stanislav/karton_memory_watcher
Classifier: Programming Language :: Python :: 3
Classifier: License :: OSI Approved :: MIT License
Classifier: Operating System :: OS Independent
Requires-Python: >=3.7
Requires-Dist: karton-core>=5.0.0
Requires-Dist: psutil>=5.9.0
